cocup/__init__.py
cocup/__main__.py
cocup/builder.py
cocup/main.py
cocup/parser/__init__.py
cocup/parser/parser.py
cocup/templates/licenses/apache2.txt
cocup/templates/licenses/gpl3.txt
cocup/templates/misc/gitignore
cocup/templates/python/errors.py
cocup/templates/python/main.py
cocup/templates/python/parser.py
cocup/templates/python/setup.py
cocup-0.1.2.dist-info/licenses/LICENSE
cocup-0.1.2.dist-info/METADATA
cocup-0.1.2.dist-info/WHEEL
cocup-0.1.2.dist-info/entry_points.txt
cocup-0.1.2.dist-info/top_level.txt
cocup-0.1.2.dist-info/RECORD
