Metadata-Version: 2.4
Name: cocup
Version: 0.1.2
Summary: Thom's COokie CUtter for Python
Author: Thomas J. Booth
Author-email: thoboo@biosustain.dtu.dk
Requires-Python: >=3.10
License-File: LICENSE
Dynamic: author
Dynamic: author-email
Dynamic: description
Dynamic: description-content-type
Dynamic: license-file
Dynamic: requires-python
Dynamic: summary
